commandfile/__init__.py
commandfile/argparse.py
commandfile/io.py
commandfile/model.py
commandfile/data/schema.json
commandfile_tmp-0.3.0.dist-info/METADATA
commandfile_tmp-0.3.0.dist-info/WHEEL
commandfile_tmp-0.3.0.dist-info/top_level.txt
commandfile_tmp-0.3.0.dist-info/RECORD
