Metadata-Version: 2.4
Name: commandfile-tmp
Version: 0.3.0
Summary: Command file for scientific workflows.
License-Expression: Apache-2.0
Requires-Python: >=3.11
Requires-Dist: pydantic
Requires-Dist: pyyaml
